VEDXXIII/__init__.py
VEDXXIII/trialpdf.py
VEDXXIII-0.0.1.dist-info/License.txt
VEDXXIII-0.0.1.dist-info/METADATA
VEDXXIII-0.0.1.dist-info/WHEEL
VEDXXIII-0.0.1.dist-info/top_level.txt
VEDXXIII-0.0.1.dist-info/RECORD
