Metadata-Version: 2.1
Name: VEDXXIII
Version: 0.0.1
Summary: UNKNOWN
Home-page: UNKNOWN
Author: Vedashree Joshi
Author-email: vedashreejoshi20@gmail.com
License: MIT
Platform: UNKNOWN
Classifier: Programming Language :: Python :: 3
Classifier: License :: OSI Approved :: MIT License
Classifier: Operating System :: OS Independent
License-File: License.txt
